eyja_redis/__init__.py
eyja_redis/client.py
eyja_redis/config.py
tests/__init__.py
tests/test_client.py
eyja_redis-0.1.1.dist-info/METADATA
eyja_redis-0.1.1.dist-info/WHEEL
eyja_redis-0.1.1.dist-info/top_level.txt
eyja_redis-0.1.1.dist-info/zip-safe
eyja_redis-0.1.1.dist-info/RECORD
