Metadata-Version: 2.1
Name: eyja-redis
Version: 0.1.1
Summary: Redis Plugin for Eyja
Home-page: https://gitlab.com/public.eyja.dev/eyja-redis
Maintainer: Anton Berdnikov
Maintainer-email: agratoth@yandex.ru
License: UNKNOWN
Platform: UNKNOWN
Classifier: License :: OSI Approved :: MIT License
Classifier: Operating System :: OS Independent
Classifier: Programming Language :: Python
Classifier: Programming Language :: Python :: 3.8
Classifier: Programming Language :: Python :: 3.9
Requires-Python: >=3.8
Requires-Dist: eyja-internal (>==0.3.14)
Requires-Dist: aioredis (>=2.0.0)
Requires-Dist: python-slugify (>=5.0.2)
